[
  {
    "id": "ladywhite",
    "brand": "Lady White Co",
    "name": "Our T-Shirt",
    "price": 90,
    "color": "White",
    "material": "100% Cotton",
    "origin": "Los Angeles",
    "url": "https://www.ladywhiteco.com/collections/t-shirts",
    "image_url": null,
    "url_verified": true,
    "url_status": 200,
    "image_downloaded": false,
    "notes": ""
  },
  {
    "id": "sunspel",
    "brand": "Sunspel",
    "name": "Riviera Polo",
    "price": 115,
    "color": "White",
    "material": "Cotton",
    "origin": "England",
    "url": "https://www.sunspel.com/us/mens/polos",
    "image_url": null,
    "url_verified": false,
    "url_status": 404,
    "image_downloaded": false,
    "notes": "URL returned 404"
  },
  {
    "id": "drakes",
    "brand": "Drake's",
    "name": "Oxford BD Shirt",
    "price": 295,
    "color": "Light Blue",
    "material": "Oxford Cotton",
    "origin": "England",
    "url": "https://www.drakes.com/usa/shirts",
    "image_url": null,
    "url_verified": true,
    "url_status": 200,
    "image_downloaded": false,
    "notes": ""
  },
  {
    "id": "lucafaloni",
    "brand": "Luca Faloni",
    "name": "Cashmere Crewneck",
    "price": 395,
    "color": "Light Grey",
    "material": "100% Cashmere",
    "origin": "Italy",
    "url": "https://www.lucafaloni.com/collections/cashmere",
    "image_url": null,
    "url_verified": true,
    "url_status": 200,
    "image_downloaded": false,
    "notes": ""
  },
  {
    "id": "ironheart",
    "brand": "Iron Heart",
    "name": "21oz Selvedge Denim",
    "price": 395,
    "color": "Indigo",
    "material": "21oz Selvedge Denim",
    "origin": "Japan",
    "url": "https://www.ironheartamerica.com/bottoms/",
    "image_url": null,
    "url_verified": true,
    "url_status": 200,
    "image_downloaded": false,
    "notes": ""
  },
  {
    "id": "burberry",
    "brand": "Burberry",
    "name": "Kensington Trench",
    "price": 2290,
    "color": "Honey",
    "material": "Cotton Gabardine",
    "origin": "England",
    "url": "https://us.burberry.com/mens-trench-coats/",
    "image_url": null,
    "url_verified": false,
    "url_status": 404,
    "image_downloaded": false,
    "notes": "URL returned 404"
  },
  {
    "id": "schott",
    "brand": "Schott NYC",
    "name": "Perfecto 618",
    "price": 900,
    "color": "Black",
    "material": "Steerhide Leather",
    "origin": "USA",
    "url": "https://www.schottnyc.com/products/classic-perfecto-steerhide-leather-motorcycle-jacket.htm",
    "image_url": null,
    "url_verified": true,
    "url_status": 200,
    "image_downloaded": false,
    "notes": ""
  },
  {
    "id": "barbour",
    "brand": "Barbour",
    "name": "Bedale Waxed Jacket",
    "price": 450,
    "color": "Olive",
    "material": "Waxed Cotton",
    "origin": "England",
    "url": "https://www.barbour.com/us/barbour-bedale-wax-jacket",
    "image_url": null,
    "url_verified": false,
    "url_status": 404,
    "image_downloaded": false,
    "notes": "URL returned 404"
  },
  {
    "id": "cp",
    "brand": "Common Projects",
    "name": "Achilles Low",
    "price": 450,
    "color": "White",
    "material": "Nappa Leather",
    "origin": "Italy",
    "url": "https://www.mrporter.com/en-us/mens/designer/common-projects",
    "image_url": null,
    "url_verified": false,
    "url_status": 0,
    "image_downloaded": false,
    "notes": "Timeout"
  },
  {
    "id": "alden",
    "brand": "Alden",
    "name": "990 Plain Toe Blucher",
    "price": 799,
    "color": "Color 8",
    "material": "Shell Cordovan",
    "origin": "USA",
    "url": "https://www.theshoemart.com/alden-mens-990-plain-toe-blucher-color-8-shell-cordovan/",
    "image_url": null,
    "url_verified": true,
    "url_status": 200,
    "image_downloaded": false,
    "notes": ""
  },
  {
    "id": "edwardgreen",
    "brand": "Edward Green",
    "name": "Chelsea Boot",
    "price": 1495,
    "color": "Dark Oak",
    "material": "Calf Leather",
    "origin": "England",
    "url": "https://www.edwardgreen.com/shop/shoes/chelsea-dark-oak-antique-82-last.html",
    "image_url": null,
    "url_verified": false,
    "url_status": 404,
    "image_downloaded": false,
    "notes": "URL returned 404"
  },
  {
    "id": "grandseiko",
    "brand": "Grand Seiko",
    "name": "Snowflake SBGA211",
    "price": 5800,
    "color": "White Dial",
    "material": "Titanium",
    "origin": "Japan",
    "url": "https://www.grand-seiko.com/us-en/collections/sbga211g",
    "image_url": null,
    "url_verified": true,
    "url_status": 200,
    "image_downloaded": false,
    "notes": ""
  },
  {
    "id": "persol",
    "brand": "Persol",
    "name": "714 Steve McQueen",
    "price": 340,
    "color": "Havana",
    "material": "Acetate",
    "origin": "Italy",
    "url": "https://www.persol.com/usa/0PO0714-24-31.html",
    "image_url": null,
    "url_verified": false,
    "url_status": 403,
    "image_downloaded": false,
    "notes": "URL returned 403"
  },
  {
    "id": "andersons",
    "brand": "Anderson's",
    "name": "Woven Leather Belt",
    "price": 195,
    "color": "Tan",
    "material": "Woven Leather",
    "origin": "Italy",
    "url": "https://www.andersonsbelt.com/collections/braided-leather-belts",
    "image_url": null,
    "url_verified": false,
    "url_status": 0,
    "image_downloaded": false,
    "notes": "Cannot connect to host www.andersonsbelt.com:443 s"
  },
  {
    "id": "frankclegg",
    "brand": "Frank Clegg",
    "name": "Zip-Top Briefcase",
    "price": 1100,
    "color": "Chestnut",
    "material": "Full Grain Leather",
    "origin": "USA",
    "url": "https://frankclegg.com/collections/briefcases/products/zip-top-briefcase",
    "image_url": null,
    "url_verified": true,
    "url_status": 200,
    "image_downloaded": false,
    "notes": ""
  }
]